elicit/__init__.py
elicit/elicit.py
elicit/extras/__init__.py
elicit/extras/utils.py
elicit/initialization.py
elicit/losses.py
elicit/networks.py
elicit/optimization.py
elicit/plots.py
elicit/simulations.py
elicit/targets.py
elicit/types.py
elicit/utils.py
elicits-0.0.7.dist-info/LICENSE
elicits-0.0.7.dist-info/LICENSES/Apache-2.0.txt
elicits-0.0.7.dist-info/LICENSES/CC-BY-4.0.txt
elicits-0.0.7.dist-info/METADATA
elicits-0.0.7.dist-info/WHEEL
elicits-0.0.7.dist-info/RECORD
