Metadata-Version: 2.1
Name: elicits
Version: 0.0.7
Summary: Tool for learning prior distributions based on expert knowledge
License: Apache-2.0
Author: Florence Bockting
Author-email: florence.bockting@tu-dortmund.de
Maintainer: Florence Bockting
Maintainer-email: florence.bockting@tu-dortmund.de
Requires-Python: >=3.10,<3.12
Classifier: License :: OSI Approved :: Apache Software License
Classifier: Programming Language :: Python :: 3
Classifier: Programming Language :: Python :: 3.10
Classifier: Programming Language :: Python :: 3.11
Requires-Dist: bayesflow (==1.1.6)
Requires-Dist: configs (==3.0.3)
Requires-Dist: defusedxml (==0.7.1)
Requires-Dist: genbadge (==1.1.1)
Requires-Dist: joblib (==1.4.2)
Requires-Dist: matplotlib (==3.10.0)
Requires-Dist: myst_nb (==1.1.0)
Requires-Dist: numpy (==1.26.4)
Requires-Dist: numpydoc (==1.7.0)
Requires-Dist: pandas (==2.2.3)
Requires-Dist: poetry-core
Requires-Dist: pyarrow (==16.1.0)
Requires-Dist: python-json-logger (==2.0.7)
Requires-Dist: scipy (==1.15.2)
Requires-Dist: signac (==2.2.0)
Requires-Dist: sphinx (==7.3.7)
Requires-Dist: sphinx-book-theme (==1.1.2)
Requires-Dist: sphinx-pyproject (==0.3.0)
Requires-Dist: sphinx_design (==0.6.0)
Requires-Dist: sphinxemoji (==0.3.1)
Requires-Dist: tensorflow (==2.15.1)
Requires-Dist: tensorflow-io-gcs-filesystem (==0.31.0)
Requires-Dist: tensorflow-probability (==0.23.0)
Requires-Dist: tqdm (==4.67.1)
